AUTHORS.rst
CHANGELOG.rst
MANIFEST.in
README.rst
setup.py
django_setuptest_recipe/__init__.py
django_setuptest_recipe/recipe.py
django_setuptest_recipe.egg-info/PKG-INFO
django_setuptest_recipe.egg-info/SOURCES.txt
django_setuptest_recipe.egg-info/dependency_links.txt
django_setuptest_recipe.egg-info/entry_points.txt
django_setuptest_recipe.egg-info/not-zip-safe
django_setuptest_recipe.egg-info/requires.txt
django_setuptest_recipe.egg-info/top_level.txt