Metadata-Version: 1.0
Name: django-setuptest-recipe
Version: 0.1
Summary: Recipe to prevent django-setuptest from polluting module being tested with downloaded eggs
Home-page: http://github.com/praekelt/django-setuptest-recipe
Author: Praekelt Foundation
Author-email: dev@praekelt.com
License: BSD
Platform: UNKNOWN
Classifier: Programming Language :: Python
Classifier: License :: OSI Approved :: BSD License
Classifier: Development Status :: 4 - Beta
Classifier: Operating System :: OS Independent
Classifier: Framework :: Django
Classifier: Intended Audience :: Developers
Classifier: Topic :: Internet :: WWW/HTTP :: Dynamic Content
